panviva/__init__.py
panviva/api_client.py
panviva/configuration.py
panviva/rest.py
panviva/api/__init__.py
panviva/api/operations_api.py
panviva/api/resources_api.py
panviva/models/__init__.py
panviva/models/artefact_category.py
panviva/models/category.py
panviva/models/channel.py
panviva/models/container.py
panviva/models/container_relationship.py
panviva/models/document.py
panviva/models/facet.py
panviva/models/folder.py
panviva/models/get_artefact_categories_response.py
panviva/models/get_container_response.py
panviva/models/get_document_container_relationships_response.py
panviva/models/get_document_containers_response.py
panviva/models/get_document_response.py
panviva/models/get_document_translations_response.py
panviva/models/get_file_response.py
panviva/models/get_folder_children_response.py
panviva/models/get_folder_response.py
panviva/models/get_folder_root_response.py
panviva/models/get_folder_translations_response.py
panviva/models/get_image_response.py
panviva/models/get_response_response.py
panviva/models/get_search_artefact_response.py
panviva/models/get_search_response.py
panviva/models/link.py
panviva/models/meta_data_value_details.py
panviva/models/post_artefact_category_request.py
panviva/models/post_artefact_category_response.py
panviva/models/post_live_csh_request.py
panviva/models/post_live_csh_response.py
panviva/models/post_live_document_request.py
panviva/models/post_live_document_response.py
panviva/models/post_live_search_request.py
panviva/models/post_live_search_response.py
panviva/models/query_variation.py
panviva/models/resource.py
panviva/models/resource_search_result.py
panviva/models/response_section.py
panviva/models/response_variation.py
panviva/models/search_result.py
panviva/models/string_int64_nullable_key_value_pair.py
panviva/models/tag.py
panviva/models/training.py
test/__init__.py
test/test_artefact_category.py
test/test_category.py
test/test_channel.py
test/test_container.py
test/test_container_relationship.py
panviva-1.0.2.dist-info/METADATA
panviva-1.0.2.dist-info/WHEEL
panviva-1.0.2.dist-info/top_level.txt
panviva-1.0.2.dist-info/RECORD
