Metadata-Version: 2.1
Name: panviva
Version: 1.0.2
Summary: A simple package provided by Panviva to help streamline integrations with Panviva APIs within Python environments.
Home-page: https://github.com/panviva/toolkit-python-sdk
Author: UNKNOWN
Author-email: support@panviva.com
License: UNKNOWN
Keywords: Panviva
Platform: UNKNOWN
Requires-Dist: certifi (>=2017.4.17)
Requires-Dist: python-dateutil (>=2.1)
Requires-Dist: six (>=1.10)
Requires-Dist: urllib3 (>=1.23)
